vnac/__init__.py
vnac/corrector.py
vnac/schemas.py
vnac/utils.py
vnac-0.1.2.dist-info/METADATA
vnac-0.1.2.dist-info/WHEEL
vnac-0.1.2.dist-info/RECORD
