Metadata-Version: 2.1
Name: vnac
Version: 0.1.2
Summary: 
Home-page: https://github.com/jasonntn/VNAddressCorrector
Keywords: Vietnam,division,address,locality
Author: Ngô Trần Ngọc Sơn
Author-email: ntns1607@gmail.com
Requires-Python: >=3.8,<4.0
Classifier: Development Status :: 4 - Beta
Classifier: Intended Audience :: Developers
Classifier: Intended Audience :: Information Technology
Classifier: Natural Language :: Vietnamese
Classifier: Operating System :: OS Independent
Classifier: Programming Language :: Python :: 3
Classifier: Programming Language :: Python :: 3.8
Classifier: Programming Language :: Python :: 3.9
Classifier: Programming Language :: Python :: 3.10
Classifier: Programming Language :: Python :: 3.11
Classifier: Programming Language :: Python :: 3 :: Only
Classifier: Topic :: Software Development :: Libraries :: Python Modules
Classifier: Topic :: Software Development :: Localization
Requires-Dist: loguru (>=0.7.0,<0.8.0)
Requires-Dist: python-rapidjson (>=1.10,<2.0)
Requires-Dist: rapidfuzz (>=3.1.2,<4.0.0)
Requires-Dist: vietnam-provinces (>=0.5.0,<0.6.0)
Project-URL: Repository, https://github.com/jasonntn/VNAddressCorrector
